<?xml version="1.0" encoding="UTF-8"?>
<objects serializationModel="Studio.02.02.00">
	<object class="AudioFile" id="{290a9707-fe9c-4be8-ada3-d8b08f2dcf3a}">
		<property name="assetPath">
			<value>SFX/Player/Footsteps/Concrete/Walk/ralphwhitehead__footsteps-walking-on-concrete-floor-medium-pace-6.wav</value>
		</property>
		<property name="frequencyInKHz">
			<value>48</value>
		</property>
		<property name="channelCount">
			<value>2</value>
		</property>
		<property name="length">
			<value>0.49287500000000001</value>
		</property>
		<relationship name="masterAssetFolder">
			<destination>{27e0664f-3dab-41da-8798-4da8ed25d478}</destination>
		</relationship>
	</object>
</objects>
