<?xml version="1.0" encoding="UTF-8"?>
<objects serializationModel="Studio.02.02.00">
	<object class="AudioFile" id="{38eec202-90e9-4797-bbba-69d031e227ec}">
		<property name="assetPath">
			<value>SFX/Player/Footsteps/Wood/Run/ralphwhitehead__footsteps-running-on-wooden-floor-fast-pace-20.wav</value>
		</property>
		<property name="frequencyInKHz">
			<value>48</value>
		</property>
		<property name="channelCount">
			<value>2</value>
		</property>
		<property name="length">
			<value>0.21389583333333334</value>
		</property>
		<relationship name="masterAssetFolder">
			<destination>{27e0664f-3dab-41da-8798-4da8ed25d478}</destination>
		</relationship>
	</object>
</objects>
